hamcontestanalysis/__init__.py
hamcontestanalysis/__main__.py
hamcontestanalysis/cli/__init__.py
hamcontestanalysis/cli/dashboard.py
hamcontestanalysis/cli/download.py
hamcontestanalysis/cli/main.py
hamcontestanalysis/cli/plot.py
hamcontestanalysis/commons/__init__.py
hamcontestanalysis/commons/logging.py
hamcontestanalysis/commons/pandas/__init__.py
hamcontestanalysis/commons/pandas/arrldx.py
hamcontestanalysis/commons/pandas/cqwpx.py
hamcontestanalysis/commons/pandas/cqww.py
hamcontestanalysis/commons/pandas/general.py
hamcontestanalysis/commons/pandas/iaru.py
hamcontestanalysis/config/__init__.py
hamcontestanalysis/config/base.py
hamcontestanalysis/config/contest.py
hamcontestanalysis/config/info.py
hamcontestanalysis/config/logging.py
hamcontestanalysis/config/settings.py
hamcontestanalysis/config/storage.py
hamcontestanalysis/data/__init__.py
hamcontestanalysis/data/arrldx/__init__.py
hamcontestanalysis/data/arrldx/storage_source.py
hamcontestanalysis/data/cqwpx/__init__.py
hamcontestanalysis/data/cqwpx/storage_source.py
hamcontestanalysis/data/cqww/__init__.py
hamcontestanalysis/data/cqww/storage_source.py
hamcontestanalysis/data/data_sink.py
hamcontestanalysis/data/data_source.py
hamcontestanalysis/data/iaru/__init__.py
hamcontestanalysis/data/iaru/storage_source.py
hamcontestanalysis/data/processed_contest_source.py
hamcontestanalysis/data/processed_rbn_source.py
hamcontestanalysis/data/raw_contest_cabrillo.py
hamcontestanalysis/data/raw_contest_sink.py
hamcontestanalysis/data/raw_rbn_sink.py
hamcontestanalysis/data/rbn/__init__.py
hamcontestanalysis/data/rbn/storage_source.py
hamcontestanalysis/data/storage_sink.py
hamcontestanalysis/data/storage_source.py
hamcontestanalysis/modules/__init__.py
hamcontestanalysis/modules/dashboard/__init__.py
hamcontestanalysis/modules/dashboard/assets/css/test.css
hamcontestanalysis/modules/dashboard/callbacks/__init__.py
hamcontestanalysis/modules/dashboard/callbacks/search.py
hamcontestanalysis-1.1.0.dist-info/LICENSE
hamcontestanalysis-1.1.0.dist-info/METADATA
hamcontestanalysis-1.1.0.dist-info/WHEEL
hamcontestanalysis-1.1.0.dist-info/entry_points.txt
hamcontestanalysis-1.1.0.dist-info/RECORD
