Metadata-Version: 2.1
Name: hamcontestanalysis
Version: 1.1.0
Summary: Ham radio contest analysis tools
Home-page: https://github.com/rogercaminal/hamcontestanalysis
License: MIT
Author: Roger Caminal Armadans
Author-email: roger.caminal@gmail.com
Requires-Python: >=3.8,<4.0
Classifier: Development Status :: 1 - Planning
Classifier: License :: OSI Approved :: MIT License
Classifier: Programming Language :: Python :: 3
Classifier: Programming Language :: Python :: 3.8
Classifier: Programming Language :: Python :: 3.9
Classifier: Programming Language :: Python :: 3.10
Classifier: Programming Language :: Python :: 3.11
Classifier: Programming Language :: Python :: 3.12
Requires-Dist: click (>=8.0.1)
Requires-Dist: dash (==2.11.0)
Requires-Dist: dash-bootstrap-components (==1.4.1)
Requires-Dist: dynaconf (==3.1.12)
Requires-Dist: pandas (==2.0.0)
Requires-Dist: pyarrow (==12.0.1)
Requires-Dist: pydantic (==1.10.7)
Requires-Dist: pyhamtools (==0.8.7)
Requires-Dist: python-dotenv (==1.0.1)
Requires-Dist: sphinxcontrib-typer (==0.2.1)
Requires-Dist: typer (==0.9.0)
Project-URL: Changelog, https://github.com/rogercaminal/hamcontestanalysis/releases
Project-URL: Documentation, https://hamcontestanalysis.readthedocs.io
Project-URL: Repository, https://github.com/rogercaminal/hamcontestanalysis
